tailctx/__init__.py
tailctx/__main__.py
tailctx/commands/__init__.py
tailctx/commands/config.py
tailctx/commands/connect.py
tailctx/commands/status.py
tailctx/tailctx.py
tailctx/tailscale.py
tailctx/util/__init__.py
tailctx/util/colors.py
tailctx/util/display.py
tailctx-0.8.0.dist-info/LICENSE
tailctx-0.8.0.dist-info/METADATA
tailctx-0.8.0.dist-info/WHEEL
tailctx-0.8.0.dist-info/entry_points.txt
tailctx-0.8.0.dist-info/RECORD
