Metadata-Version: 2.1
Name: tailctx
Version: 0.8.0
Summary: Tailscale Context Manager
Home-page: https://github.com/apognu/tailctx
License: MIT
Author: Antoine POPINEAU
Author-email: antoine@popineau.eu
Requires-Python: >=3.10,<4.0
Classifier: License :: OSI Approved :: MIT License
Classifier: Programming Language :: Python :: 3
Classifier: Programming Language :: Python :: 3.10
Classifier: Programming Language :: Python :: 3.11
Classifier: Programming Language :: Python :: 3.12
Classifier: Topic :: Security
Classifier: Topic :: Utilities
Requires-Dist: prettytable (>=3.3.0,<4.0.0)
Requires-Dist: tailscale-localapi (>=0.5.0,<0.6.0)
Requires-Dist: termcolor (>=1.1.0,<2.0.0)
Project-URL: Repository, https://github.com/apognu/tailctx
